MANIFEST.in
setup.py
include/mummy.h
lib/dump.c
lib/load.c
lib/mummy_string.c
lzf/lzf.h
lzf/lzfP.h
lzf/lzf_c.c
lzf/lzf_d.c
python/_old_mummy.c
python/dump.c
python/load.c
python/mummymodule.c
python/mummypy.h
python/mummy/__init__.py
python/mummy/django_serialization.py
python/mummy/schemas.py
python/mummy/serialization.py
python/mummy.egg-info/PKG-INFO
python/mummy.egg-info/SOURCES.txt
python/mummy.egg-info/dependency_links.txt
python/mummy.egg-info/top_level.txt
python/oldmummy/__init__.py
python/oldmummy/schemas.py
python/oldmummy/serialization.py