Metadata-Version: 1.1
Name: mummy
Version: 1.0.3
Summary: fast, efficient serialization
Home-page: http://github.com/teepark/mummy
Author: Travis Parker
Author-email: travis.parker@gmail.com
License: BSD
Platform: UNKNOWN
Classifier: Development Status :: 5 - Production/Stable
Classifier: Intended Audience :: Developers
Classifier: License :: OSI Approved :: BSD License
Classifier: Natural Language :: English
Classifier: Programming Language :: C
Classifier: Programming Language :: Python
